semsimian-0.2.19.dist-info/METADATA
semsimian-0.2.19.dist-info/WHEEL
semsimian-0.2.19.dist-info/license_files/LICENSE
semsimian/__init__.py
semsimian/semsimian.cpython-311-aarch64-linux-gnu.so
semsimian-0.2.19.dist-info/RECORD
