Metadata-Version: 2.1
Name: semsimian
Version: 0.2.19
Classifier: Programming Language :: Rust
Classifier: Programming Language :: Python :: Implementation :: CPython
Classifier: Programming Language :: Python :: Implementation :: PyPy
License-File: LICENSE
Summary: Sematic similarity calculations for ontologies implemented in Rust.
License: BSD-3-Clause
Requires-Python: >=3.7
